<annotation>
  <folder>Images</folder>
  <filename>005249.jpg</filename>
  <size>
    <width>980</width>
    <height>1386</height>
    <depth>005249.jpg</depth>
  </size>
  <object>
    <name>7</name>
    <difficult>0</difficult>
    <bndbox>
      <xmin>870.0</xmin>
      <ymin>41.0</ymin>
      <xmax>892.0</xmax>
      <ymax>75.0</ymax>
    </bndbox>
  </object>
  <object>
    <name>2</name>
    <difficult>0</difficult>
    <bndbox>
      <xmin>846.0</xmin>
      <ymin>43.0</ymin>
      <xmax>869.0</xmax>
      <ymax>74.0</ymax>
    </bndbox>
  </object>
  <object>
    <name>Single_barline</name>
    <difficult>0</difficult>
    <bndbox>
      <xmin>876.0</xmin>
      <ymin>142.0</ymin>
      <xmax>894.0</xmax>
      <ymax>209.0</ymax>
    </bndbox>
  </object>
  <object>
    <name>Single_barline</name>
    <difficult>0</difficult>
    <bndbox>
      <xmin>876.0</xmin>
      <ymin>1190.0</ymin>
      <xmax>893.0</xmax>
      <ymax>1257.0</ymax>
    </bndbox>
  </object>
  <object>
    <name>Rests1</name>
    <difficult>0</difficult>
    <bndbox>
      <xmin>386.0</xmin>
      <ymin>154.0</ymin>
      <xmax>429.0</xmax>
      <ymax>175.0</ymax>
    </bndbox>
  </object>
  <object>
    <name>Rests1</name>
    <difficult>0</difficult>
    <bndbox>
      <xmin>386.0</xmin>
      <ymin>1201.0</ymin>
      <xmax>429.0</xmax>
      <ymax>1223.0</ymax>
    </bndbox>
  </object>
</annotation>
