<annotation>
  <folder>Images</folder>
  <filename>005836.jpg</filename>
  <size>
    <width>2970</width>
    <height>2100</height>
    <depth>005836.jpg</depth>
  </size>
  <object>
    <name>2</name>
    <difficult>0</difficult>
    <bndbox>
      <xmin>140.0</xmin>
      <ymin>66.0</ymin>
      <xmax>162.0</xmax>
      <ymax>97.0</ymax>
    </bndbox>
  </object>
  <object>
    <name>1</name>
    <difficult>0</difficult>
    <bndbox>
      <xmin>110.0</xmin>
      <ymin>131.0</ymin>
      <xmax>123.0</xmax>
      <ymax>157.0</ymax>
    </bndbox>
  </object>
  <object>
    <name>5</name>
    <difficult>0</difficult>
    <bndbox>
      <xmin>127.0</xmin>
      <ymin>131.0</ymin>
      <xmax>142.0</xmax>
      <ymax>156.0</ymax>
    </bndbox>
  </object>
  <object>
    <name>D_S</name>
    <difficult>0</difficult>
    <bndbox>
      <xmin>212.0</xmin>
      <ymin>145.0</ymin>
      <xmax>251.0</xmax>
      <ymax>222.0</ymax>
    </bndbox>
  </object>
  <object>
    <name>Bracke</name>
    <difficult>0</difficult>
    <bndbox>
      <xmin>112.0</xmin>
      <ymin>158.0</ymin>
      <xmax>149.0</xmax>
      <ymax>842.0</ymax>
    </bndbox>
  </object>
  <object>
    <name>Brace</name>
    <difficult>0</difficult>
    <bndbox>
      <xmin>96.0</xmin>
      <ymin>162.0</ymin>
      <xmax>115.0</xmax>
      <ymax>425.0</ymax>
    </bndbox>
  </object>
  <object>
    <name>Single_barline</name>
    <difficult>0</difficult>
    <bndbox>
      <xmin>134.0</xmin>
      <ymin>172.0</ymin>
      <xmax>151.0</xmax>
      <ymax>239.0</ymax>
    </bndbox>
  </object>
  <object>
    <name>Single_barline</name>
    <difficult>0</difficult>
    <bndbox>
      <xmin>1094.0</xmin>
      <ymin>172.0</ymin>
      <xmax>1112.0</xmax>
      <ymax>239.0</ymax>
    </bndbox>
  </object>
  <object>
    <name>Single_barline</name>
    <difficult>0</difficult>
    <bndbox>
      <xmin>1980.0</xmin>
      <ymin>172.0</ymin>
      <xmax>1998.0</xmax>
      <ymax>240.0</ymax>
    </bndbox>
  </object>
  <object>
    <name>Single_barline</name>
    <difficult>0</difficult>
    <bndbox>
      <xmin>2816.0</xmin>
      <ymin>172.0</ymin>
      <xmax>2836.0</xmax>
      <ymax>239.0</ymax>
    </bndbox>
  </object>
  <object>
    <name>Staccatissimo</name>
    <difficult>0</difficult>
    <bndbox>
      <xmin>2119.0</xmin>
      <ymin>243.0</ymin>
      <xmax>2141.0</xmax>
      <ymax>264.0</ymax>
    </bndbox>
  </object>
  <object>
    <name>Crescendo_hairpin</name>
    <difficult>0</difficult>
    <bndbox>
      <xmin>2046.0</xmin>
      <ymin>264.0</ymin>
      <xmax>2192.0</xmax>
      <ymax>294.0</ymax>
    </bndbox>
  </object>
  <object>
    <name>D_S</name>
    <difficult>0</difficult>
    <bndbox>
      <xmin>212.0</xmin>
      <ymin>333.0</ymin>
      <xmax>253.0</xmax>
      <ymax>411.0</ymax>
    </bndbox>
  </object>
  <object>
    <name>Single_barline</name>
    <difficult>0</difficult>
    <bndbox>
      <xmin>134.0</xmin>
      <ymin>360.0</ymin>
      <xmax>151.0</xmax>
      <ymax>428.0</ymax>
    </bndbox>
  </object>
  <object>
    <name>Single_barline</name>
    <difficult>0</difficult>
    <bndbox>
      <xmin>1094.0</xmin>
      <ymin>360.0</ymin>
      <xmax>1112.0</xmax>
      <ymax>429.0</ymax>
    </bndbox>
  </object>
  <object>
    <name>Single_barline</name>
    <difficult>0</difficult>
    <bndbox>
      <xmin>1980.0</xmin>
      <ymin>360.0</ymin>
      <xmax>2000.0</xmax>
      <ymax>428.0</ymax>
    </bndbox>
  </object>
  <object>
    <name>Single_barline</name>
    <difficult>0</difficult>
    <bndbox>
      <xmin>2816.0</xmin>
      <ymin>361.0</ymin>
      <xmax>2836.0</xmax>
      <ymax>427.0</ymax>
    </bndbox>
  </object>
  <object>
    <name>D_S</name>
    <difficult>0</difficult>
    <bndbox>
      <xmin>212.0</xmin>
      <ymin>545.0</ymin>
      <xmax>253.0</xmax>
      <ymax>624.0</ymax>
    </bndbox>
  </object>
  <object>
    <name>Single_barline</name>
    <difficult>0</difficult>
    <bndbox>
      <xmin>1093.0</xmin>
      <ymin>572.0</ymin>
      <xmax>1112.0</xmax>
      <ymax>641.0</ymax>
    </bndbox>
  </object>
  <object>
    <name>Single_barline</name>
    <difficult>0</difficult>
    <bndbox>
      <xmin>1979.0</xmin>
      <ymin>572.0</ymin>
      <xmax>2001.0</xmax>
      <ymax>642.0</ymax>
    </bndbox>
  </object>
  <object>
    <name>Single_barline</name>
    <difficult>0</difficult>
    <bndbox>
      <xmin>134.0</xmin>
      <ymin>573.0</ymin>
      <xmax>152.0</xmax>
      <ymax>640.0</ymax>
    </bndbox>
  </object>
  <object>
    <name>Single_barline</name>
    <difficult>0</difficult>
    <bndbox>
      <xmin>2817.0</xmin>
      <ymin>573.0</ymin>
      <xmax>2835.0</xmax>
      <ymax>640.0</ymax>
    </bndbox>
  </object>
  <object>
    <name>D_S</name>
    <difficult>0</difficult>
    <bndbox>
      <xmin>213.0</xmin>
      <ymin>732.0</ymin>
      <xmax>253.0</xmax>
      <ymax>811.0</ymax>
    </bndbox>
  </object>
  <object>
    <name>Single_barline</name>
    <difficult>0</difficult>
    <bndbox>
      <xmin>135.0</xmin>
      <ymin>742.0</ymin>
      <xmax>153.0</xmax>
      <ymax>811.0</ymax>
    </bndbox>
  </object>
  <object>
    <name>Single_barline</name>
    <difficult>0</difficult>
    <bndbox>
      <xmin>1093.0</xmin>
      <ymin>743.0</ymin>
      <xmax>1112.0</xmax>
      <ymax>810.0</ymax>
    </bndbox>
  </object>
  <object>
    <name>Single_barline</name>
    <difficult>0</difficult>
    <bndbox>
      <xmin>1979.0</xmin>
      <ymin>743.0</ymin>
      <xmax>2001.0</xmax>
      <ymax>810.0</ymax>
    </bndbox>
  </object>
  <object>
    <name>Single_barline</name>
    <difficult>0</difficult>
    <bndbox>
      <xmin>2816.0</xmin>
      <ymin>744.0</ymin>
      <xmax>2836.0</xmax>
      <ymax>811.0</ymax>
    </bndbox>
  </object>
  <object>
    <name>D_S</name>
    <difficult>0</difficult>
    <bndbox>
      <xmin>212.0</xmin>
      <ymin>929.0</ymin>
      <xmax>252.0</xmax>
      <ymax>1006.0</ymax>
    </bndbox>
  </object>
  <object>
    <name>4_th</name>
    <difficult>0</difficult>
    <bndbox>
      <xmin>485.0</xmin>
      <ymin>938.0</ymin>
      <xmax>516.0</xmax>
      <ymax>1050.0</ymax>
    </bndbox>
  </object>
  <object>
    <name>4_th</name>
    <difficult>0</difficult>
    <bndbox>
      <xmin>2216.0</xmin>
      <ymin>938.0</ymin>
      <xmax>2246.0</xmax>
      <ymax>1049.0</ymax>
    </bndbox>
  </object>
  <object>
    <name>4_th</name>
    <difficult>0</difficult>
    <bndbox>
      <xmin>1527.0</xmin>
      <ymin>948.0</ymin>
      <xmax>1558.0</xmax>
      <ymax>1058.0</ymax>
    </bndbox>
  </object>
  <object>
    <name>Brace</name>
    <difficult>0</difficult>
    <bndbox>
      <xmin>119.0</xmin>
      <ymin>952.0</ymin>
      <xmax>138.0</xmax>
      <ymax>1194.0</ymax>
    </bndbox>
  </object>
  <object>
    <name>Single_barline</name>
    <difficult>0</difficult>
    <bndbox>
      <xmin>136.0</xmin>
      <ymin>955.0</ymin>
      <xmax>151.0</xmax>
      <ymax>1025.0</ymax>
    </bndbox>
  </object>
  <object>
    <name>4_th</name>
    <difficult>0</difficult>
    <bndbox>
      <xmin>286.0</xmin>
      <ymin>956.0</ymin>
      <xmax>319.0</xmax>
      <ymax>1066.0</ymax>
    </bndbox>
  </object>
  <object>
    <name>Single_barline</name>
    <difficult>0</difficult>
    <bndbox>
      <xmin>1093.0</xmin>
      <ymin>956.0</ymin>
      <xmax>1113.0</xmax>
      <ymax>1023.0</ymax>
    </bndbox>
  </object>
  <object>
    <name>4_th</name>
    <difficult>0</difficult>
    <bndbox>
      <xmin>1326.0</xmin>
      <ymin>956.0</ymin>
      <xmax>1357.0</xmax>
      <ymax>1066.0</ymax>
    </bndbox>
  </object>
  <object>
    <name>Single_barline</name>
    <difficult>0</difficult>
    <bndbox>
      <xmin>1979.0</xmin>
      <ymin>956.0</ymin>
      <xmax>1999.0</xmax>
      <ymax>1023.0</ymax>
    </bndbox>
  </object>
  <object>
    <name>4_th</name>
    <difficult>0</difficult>
    <bndbox>
      <xmin>2013.0</xmin>
      <ymin>956.0</ymin>
      <xmax>2046.0</xmax>
      <ymax>1065.0</ymax>
    </bndbox>
  </object>
  <object>
    <name>Single_barline</name>
    <difficult>0</difficult>
    <bndbox>
      <xmin>2816.0</xmin>
      <ymin>956.0</ymin>
      <xmax>2836.0</xmax>
      <ymax>1023.0</ymax>
    </bndbox>
  </object>
  <object>
    <name>4_th</name>
    <difficult>0</difficult>
    <bndbox>
      <xmin>890.0</xmin>
      <ymin>957.0</ymin>
      <xmax>923.0</xmax>
      <ymax>1066.0</ymax>
    </bndbox>
  </object>
  <object>
    <name>4_th</name>
    <difficult>0</difficult>
    <bndbox>
      <xmin>1779.0</xmin>
      <ymin>960.0</ymin>
      <xmax>1811.0</xmax>
      <ymax>1067.0</ymax>
    </bndbox>
  </object>
  <object>
    <name>D_S</name>
    <difficult>0</difficult>
    <bndbox>
      <xmin>214.0</xmin>
      <ymin>1115.0</ymin>
      <xmax>253.0</xmax>
      <ymax>1194.0</ymax>
    </bndbox>
  </object>
  <object>
    <name>Single_barline</name>
    <difficult>0</difficult>
    <bndbox>
      <xmin>136.0</xmin>
      <ymin>1126.0</ymin>
      <xmax>152.0</xmax>
      <ymax>1193.0</ymax>
    </bndbox>
  </object>
  <object>
    <name>Single_barline</name>
    <difficult>0</difficult>
    <bndbox>
      <xmin>1093.0</xmin>
      <ymin>1126.0</ymin>
      <xmax>1113.0</xmax>
      <ymax>1193.0</ymax>
    </bndbox>
  </object>
  <object>
    <name>Single_barline</name>
    <difficult>0</difficult>
    <bndbox>
      <xmin>1979.0</xmin>
      <ymin>1127.0</ymin>
      <xmax>1999.0</xmax>
      <ymax>1193.0</ymax>
    </bndbox>
  </object>
  <object>
    <name>Single_barline</name>
    <difficult>0</difficult>
    <bndbox>
      <xmin>2815.0</xmin>
      <ymin>1127.0</ymin>
      <xmax>2835.0</xmax>
      <ymax>1193.0</ymax>
    </bndbox>
  </object>
  <object>
    <name>Slur</name>
    <difficult>0</difficult>
    <bndbox>
      <xmin>1471.0</xmin>
      <ymin>1537.0</ymin>
      <xmax>1591.0</xmax>
      <ymax>1562.0</ymax>
    </bndbox>
  </object>
  <object>
    <name>Slur</name>
    <difficult>0</difficult>
    <bndbox>
      <xmin>1628.0</xmin>
      <ymin>1538.0</ymin>
      <xmax>1750.0</xmax>
      <ymax>1561.0</ymax>
    </bndbox>
  </object>
  <object>
    <name>8</name>
    <difficult>0</difficult>
    <bndbox>
      <xmin>126.0</xmin>
      <ymin>1541.0</ymin>
      <xmax>144.0</xmax>
      <ymax>1568.0</ymax>
    </bndbox>
  </object>
  <object>
    <name>1</name>
    <difficult>0</difficult>
    <bndbox>
      <xmin>109.0</xmin>
      <ymin>1542.0</ymin>
      <xmax>123.0</xmax>
      <ymax>1569.0</ymax>
    </bndbox>
  </object>
  <object>
    <name>Slur</name>
    <difficult>0</difficult>
    <bndbox>
      <xmin>2150.0</xmin>
      <ymin>1555.0</ymin>
      <xmax>2268.0</xmax>
      <ymax>1577.0</ymax>
    </bndbox>
  </object>
  <object>
    <name>D_S</name>
    <difficult>0</difficult>
    <bndbox>
      <xmin>212.0</xmin>
      <ymin>1559.0</ymin>
      <xmax>252.0</xmax>
      <ymax>1636.0</ymax>
    </bndbox>
  </object>
  <object>
    <name>Bracke</name>
    <difficult>0</difficult>
    <bndbox>
      <xmin>120.0</xmin>
      <ymin>1564.0</ymin>
      <xmax>156.0</xmax>
      <ymax>2100.0</ymax>
    </bndbox>
  </object>
  <object>
    <name>Brace</name>
    <difficult>0</difficult>
    <bndbox>
      <xmin>96.0</xmin>
      <ymin>1577.0</ymin>
      <xmax>115.0</xmax>
      <ymax>1836.0</ymax>
    </bndbox>
  </object>
  <object>
    <name>Single_barline</name>
    <difficult>0</difficult>
    <bndbox>
      <xmin>2817.0</xmin>
      <ymin>1584.0</ymin>
      <xmax>2835.0</xmax>
      <ymax>1653.0</ymax>
    </bndbox>
  </object>
  <object>
    <name>Single_barline</name>
    <difficult>0</difficult>
    <bndbox>
      <xmin>135.0</xmin>
      <ymin>1585.0</ymin>
      <xmax>151.0</xmax>
      <ymax>1652.0</ymax>
    </bndbox>
  </object>
  <object>
    <name>Single_barline</name>
    <difficult>0</difficult>
    <bndbox>
      <xmin>1420.0</xmin>
      <ymin>1585.0</ymin>
      <xmax>1440.0</xmax>
      <ymax>1652.0</ymax>
    </bndbox>
  </object>
  <object>
    <name>dot</name>
    <difficult>0</difficult>
    <bndbox>
      <xmin>316.0</xmin>
      <ymin>1586.0</ymin>
      <xmax>330.0</xmax>
      <ymax>1600.0</ymax>
    </bndbox>
  </object>
  <object>
    <name>Slur</name>
    <difficult>0</difficult>
    <bndbox>
      <xmin>2372.0</xmin>
      <ymin>1608.0</ymin>
      <xmax>2423.0</xmax>
      <ymax>1627.0</ymax>
    </bndbox>
  </object>
  <object>
    <name>Bracke</name>
    <difficult>0</difficult>
    <bndbox>
      <xmin>130.0</xmin>
      <ymin>1715.0</ymin>
      <xmax>152.0</xmax>
      <ymax>1892.0</ymax>
    </bndbox>
  </object>
  <object>
    <name>D_S</name>
    <difficult>0</difficult>
    <bndbox>
      <xmin>211.0</xmin>
      <ymin>1744.0</ymin>
      <xmax>253.0</xmax>
      <ymax>1821.0</ymax>
    </bndbox>
  </object>
  <object>
    <name>Single_barline</name>
    <difficult>0</difficult>
    <bndbox>
      <xmin>1420.0</xmin>
      <ymin>1769.0</ymin>
      <xmax>1441.0</xmax>
      <ymax>1838.0</ymax>
    </bndbox>
  </object>
  <object>
    <name>Single_barline</name>
    <difficult>0</difficult>
    <bndbox>
      <xmin>134.0</xmin>
      <ymin>1770.0</ymin>
      <xmax>150.0</xmax>
      <ymax>1838.0</ymax>
    </bndbox>
  </object>
  <object>
    <name>Single_barline</name>
    <difficult>0</difficult>
    <bndbox>
      <xmin>2816.0</xmin>
      <ymin>1770.0</ymin>
      <xmax>2836.0</xmax>
      <ymax>1838.0</ymax>
    </bndbox>
  </object>
  <object>
    <name>Marcato_above</name>
    <difficult>0</difficult>
    <bndbox>
      <xmin>1619.0</xmin>
      <ymin>1842.0</ymin>
      <xmax>1645.0</xmax>
      <ymax>1863.0</ymax>
    </bndbox>
  </object>
  <object>
    <name>Marcato_above</name>
    <difficult>0</difficult>
    <bndbox>
      <xmin>2299.0</xmin>
      <ymin>1860.0</ymin>
      <xmax>2323.0</xmax>
      <ymax>1880.0</ymax>
    </bndbox>
  </object>
  <object>
    <name>D_S</name>
    <difficult>0</difficult>
    <bndbox>
      <xmin>213.0</xmin>
      <ymin>1964.0</ymin>
      <xmax>251.0</xmax>
      <ymax>2041.0</ymax>
    </bndbox>
  </object>
  <object>
    <name>Single_barline</name>
    <difficult>0</difficult>
    <bndbox>
      <xmin>1419.0</xmin>
      <ymin>1981.0</ymin>
      <xmax>1440.0</xmax>
      <ymax>2049.0</ymax>
    </bndbox>
  </object>
  <object>
    <name>Single_barline</name>
    <difficult>0</difficult>
    <bndbox>
      <xmin>134.0</xmin>
      <ymin>1982.0</ymin>
      <xmax>151.0</xmax>
      <ymax>2048.0</ymax>
    </bndbox>
  </object>
  <object>
    <name>Single_barline</name>
    <difficult>0</difficult>
    <bndbox>
      <xmin>2816.0</xmin>
      <ymin>1983.0</ymin>
      <xmax>2836.0</xmax>
      <ymax>2050.0</ymax>
    </bndbox>
  </object>
  <object>
    <name>Marcato_above</name>
    <difficult>0</difficult>
    <bndbox>
      <xmin>2300.0</xmin>
      <ymin>2057.0</ymin>
      <xmax>2323.0</xmax>
      <ymax>2078.0</ymax>
    </bndbox>
  </object>
  <object>
    <name>Crescendo_hairpin</name>
    <difficult>0</difficult>
    <bndbox>
      <xmin>1137.0</xmin>
      <ymin>243.0</ymin>
      <xmax>1809.0</xmax>
      <ymax>283.0</ymax>
    </bndbox>
  </object>
  <object>
    <name>Diminuendo_hairpin</name>
    <difficult>0</difficult>
    <bndbox>
      <xmin>1325.0</xmin>
      <ymin>663.0</ymin>
      <xmax>1957.0</xmax>
      <ymax>693.0</ymax>
    </bndbox>
  </object>
  <object>
    <name>Diminuendo_hairpin</name>
    <difficult>0</difficult>
    <bndbox>
      <xmin>1463.0</xmin>
      <ymin>1861.0</ymin>
      <xmax>1749.0</xmax>
      <ymax>1895.0</ymax>
    </bndbox>
  </object>
  <object>
    <name>Crescendo_hairpin</name>
    <difficult>0</difficult>
    <bndbox>
      <xmin>857.0</xmin>
      <ymin>1663.0</ymin>
      <xmax>1313.0</xmax>
      <ymax>1695.0</ymax>
    </bndbox>
  </object>
  <object>
    <name>Slur</name>
    <difficult>0</difficult>
    <bndbox>
      <xmin>1831.0</xmin>
      <ymin>1549.0</ymin>
      <xmax>2107.0</xmax>
      <ymax>1613.0</ymax>
    </bndbox>
  </object>
  <object>
    <name>Slur</name>
    <difficult>0</difficult>
    <bndbox>
      <xmin>2471.0</xmin>
      <ymin>1525.0</ymin>
      <xmax>2799.0</xmax>
      <ymax>1549.0</ymax>
    </bndbox>
  </object>
  <object>
    <name>Vln</name>
    <difficult>0</difficult>
    <bndbox>
      <xmin>1.0</xmin>
      <ymin>186.0</ymin>
      <xmax>54.0</xmax>
      <ymax>228.0</ymax>
    </bndbox>
  </object>
  <object>
    <name>Gclef</name>
    <difficult>0</difficult>
    <bndbox>
      <xmin>154.0</xmin>
      <ymin>138.0</ymin>
      <xmax>203.0</xmax>
      <ymax>267.0</ymax>
    </bndbox>
  </object>
  <object>
    <name>8_1</name>
    <difficult>0</difficult>
    <bndbox>
      <xmin>289.0</xmin>
      <ymin>168.0</ymin>
      <xmax>313.0</xmax>
      <ymax>277.0</ymax>
    </bndbox>
  </object>
  <object>
    <name>8_8</name>
    <difficult>0</difficult>
    <bndbox>
      <xmin>379.0</xmin>
      <ymin>162.0</ymin>
      <xmax>413.0</xmax>
      <ymax>245.0</ymax>
    </bndbox>
  </object>
  <object>
    <name>mf</name>
    <difficult>0</difficult>
    <bndbox>
      <xmin>375.0</xmin>
      <ymin>250.0</ymin>
      <xmax>433.0</xmax>
      <ymax>293.0</ymax>
    </bndbox>
  </object>
  <object>
    <name>4_7</name>
    <difficult>0</difficult>
    <bndbox>
      <xmin>489.0</xmin>
      <ymin>170.0</ymin>
      <xmax>513.0</xmax>
      <ymax>241.0</ymax>
    </bndbox>
  </object>
  <object>
    <name>Rests8</name>
    <difficult>0</difficult>
    <bndbox>
      <xmin>687.0</xmin>
      <ymin>155.0</ymin>
      <xmax>712.0</xmax>
      <ymax>188.0</ymax>
    </bndbox>
  </object>
  <object>
    <name>8_6</name>
    <difficult>0</difficult>
    <bndbox>
      <xmin>792.0</xmin>
      <ymin>170.0</ymin>
      <xmax>817.0</xmax>
      <ymax>246.0</ymax>
    </bndbox>
  </object>
  <object>
    <name>4_8</name>
    <difficult>0</difficult>
    <bndbox>
      <xmin>893.0</xmin>
      <ymin>162.0</ymin>
      <xmax>918.0</xmax>
      <ymax>241.0</ymax>
    </bndbox>
  </object>
  <object>
    <name>4_11</name>
    <difficult>0</difficult>
    <bndbox>
      <xmin>1124.0</xmin>
      <ymin>136.0</ymin>
      <xmax>1152.0</xmax>
      <ymax>241.0</ymax>
    </bndbox>
  </object>
  <object>
    <name>4_10</name>
    <difficult>0</difficult>
    <bndbox>
      <xmin>1327.0</xmin>
      <ymin>144.0</ymin>
      <xmax>1355.0</xmax>
      <ymax>242.0</ymax>
    </bndbox>
  </object>
  <object>
    <name>4_11</name>
    <difficult>0</difficult>
    <bndbox>
      <xmin>1527.0</xmin>
      <ymin>136.0</ymin>
      <xmax>1556.0</xmax>
      <ymax>241.0</ymax>
    </bndbox>
  </object>
  <object>
    <name>4_12</name>
    <difficult>0</difficult>
    <bndbox>
      <xmin>1780.0</xmin>
      <ymin>129.0</ymin>
      <xmax>1808.0</xmax>
      <ymax>241.0</ymax>
    </bndbox>
  </object>
  <object>
    <name>f</name>
    <difficult>0</difficult>
    <bndbox>
      <xmin>2006.0</xmin>
      <ymin>258.0</ymin>
      <xmax>2048.0</xmax>
      <ymax>302.0</ymax>
    </bndbox>
  </object>
  <object>
    <name>8_13</name>
    <difficult>0</difficult>
    <bndbox>
      <xmin>2015.0</xmin>
      <ymin>121.0</ymin>
      <xmax>2043.0</xmax>
      <ymax>243.0</ymax>
    </bndbox>
  </object>
  <object>
    <name>8_6</name>
    <difficult>0</difficult>
    <bndbox>
      <xmin>2110.0</xmin>
      <ymin>170.0</ymin>
      <xmax>2142.0</xmax>
      <ymax>244.0</ymax>
    </bndbox>
  </object>
  <object>
    <name>mp</name>
    <difficult>0</difficult>
    <bndbox>
      <xmin>2200.0</xmin>
      <ymin>265.0</ymin>
      <xmax>2260.0</xmax>
      <ymax>301.0</ymax>
    </bndbox>
  </object>
  <object>
    <name>4_5</name>
    <difficult>0</difficult>
    <bndbox>
      <xmin>2218.0</xmin>
      <ymin>169.0</ymin>
      <xmax>2243.0</xmax>
      <ymax>256.0</ymax>
    </bndbox>
  </object>
  <object>
    <name>Rests8</name>
    <difficult>0</difficult>
    <bndbox>
      <xmin>2420.0</xmin>
      <ymin>155.0</ymin>
      <xmax>2444.0</xmax>
      <ymax>189.0</ymax>
    </bndbox>
  </object>
  <object>
    <name>8_4</name>
    <difficult>0</difficult>
    <bndbox>
      <xmin>2524.0</xmin>
      <ymin>169.0</ymin>
      <xmax>2549.0</xmax>
      <ymax>263.0</ymax>
    </bndbox>
  </object>
  <object>
    <name>4_6</name>
    <difficult>0</difficult>
    <bndbox>
      <xmin>2625.0</xmin>
      <ymin>170.0</ymin>
      <xmax>2649.0</xmax>
      <ymax>249.0</ymax>
    </bndbox>
  </object>
  <object>
    <name>Vln</name>
    <difficult>0</difficult>
    <bndbox>
      <xmin>1.0</xmin>
      <ymin>373.0</ymin>
      <xmax>54.0</xmax>
      <ymax>415.0</ymax>
    </bndbox>
  </object>
  <object>
    <name>Gclef</name>
    <difficult>0</difficult>
    <bndbox>
      <xmin>154.0</xmin>
      <ymin>326.0</ymin>
      <xmax>204.0</xmax>
      <ymax>457.0</ymax>
    </bndbox>
  </object>
  <object>
    <name>16_-1</name>
    <difficult>0</difficult>
    <bndbox>
      <xmin>288.0</xmin>
      <ymin>358.0</ymin>
      <xmax>322.0</xmax>
      <ymax>447.0</ymax>
    </bndbox>
  </object>
  <object>
    <name>16_0</name>
    <difficult>0</difficult>
    <bndbox>
      <xmin>338.0</xmin>
      <ymin>358.0</ymin>
      <xmax>366.0</xmax>
      <ymax>438.0</ymax>
    </bndbox>
  </object>
  <object>
    <name>16_1</name>
    <difficult>0</difficult>
    <bndbox>
      <xmin>388.0</xmin>
      <ymin>358.0</ymin>
      <xmax>416.0</xmax>
      <ymax>430.0</ymax>
    </bndbox>
  </object>
  <object>
    <name>16_2</name>
    <difficult>0</difficult>
    <bndbox>
      <xmin>437.0</xmin>
      <ymin>358.0</ymin>
      <xmax>464.0</xmax>
      <ymax>430.0</ymax>
    </bndbox>
  </object>
  <object>
    <name>16_3</name>
    <difficult>0</difficult>
    <bndbox>
      <xmin>487.0</xmin>
      <ymin>340.0</ymin>
      <xmax>521.0</xmax>
      <ymax>430.0</ymax>
    </bndbox>
  </object>
  <object>
    <name>16_0</name>
    <difficult>0</difficult>
    <bndbox>
      <xmin>538.0</xmin>
      <ymin>340.0</ymin>
      <xmax>565.0</xmax>
      <ymax>438.0</ymax>
    </bndbox>
  </object>
  <object>
    <name>16_3</name>
    <difficult>0</difficult>
    <bndbox>
      <xmin>589.0</xmin>
      <ymin>341.0</ymin>
      <xmax>615.0</xmax>
      <ymax>429.0</ymax>
    </bndbox>
  </object>
  <object>
    <name>16_2</name>
    <difficult>0</difficult>
    <bndbox>
      <xmin>638.0</xmin>
      <ymin>340.0</ymin>
      <xmax>664.0</xmax>
      <ymax>430.0</ymax>
    </bndbox>
  </object>
  <object>
    <name>16_1</name>
    <difficult>0</difficult>
    <bndbox>
      <xmin>686.0</xmin>
      <ymin>340.0</ymin>
      <xmax>722.0</xmax>
      <ymax>431.0</ymax>
    </bndbox>
  </object>
  <object>
    <name>16_4</name>
    <difficult>0</difficult>
    <bndbox>
      <xmin>742.0</xmin>
      <ymin>340.0</ymin>
      <xmax>768.0</xmax>
      <ymax>430.0</ymax>
    </bndbox>
  </object>
  <object>
    <name>16_3</name>
    <difficult>0</difficult>
    <bndbox>
      <xmin>792.0</xmin>
      <ymin>341.0</ymin>
      <xmax>818.0</xmax>
      <ymax>430.0</ymax>
    </bndbox>
  </object>
  <object>
    <name>16_2</name>
    <difficult>0</difficult>
    <bndbox>
      <xmin>842.0</xmin>
      <ymin>341.0</ymin>
      <xmax>868.0</xmax>
      <ymax>431.0</ymax>
    </bndbox>
  </object>
  <object>
    <name>16_3</name>
    <difficult>0</difficult>
    <bndbox>
      <xmin>892.0</xmin>
      <ymin>341.0</ymin>
      <xmax>926.0</xmax>
      <ymax>429.0</ymax>
    </bndbox>
  </object>
  <object>
    <name>16_2</name>
    <difficult>0</difficult>
    <bndbox>
      <xmin>945.0</xmin>
      <ymin>345.0</ymin>
      <xmax>972.0</xmax>
      <ymax>430.0</ymax>
    </bndbox>
  </object>
  <object>
    <name>16_1</name>
    <difficult>0</difficult>
    <bndbox>
      <xmin>997.0</xmin>
      <ymin>349.0</ymin>
      <xmax>1024.0</xmax>
      <ymax>430.0</ymax>
    </bndbox>
  </object>
  <object>
    <name>16_0</name>
    <difficult>0</difficult>
    <bndbox>
      <xmin>1047.0</xmin>
      <ymin>353.0</ymin>
      <xmax>1073.0</xmax>
      <ymax>439.0</ymax>
    </bndbox>
  </object>
  <object>
    <name>16_-1</name>
    <difficult>0</difficult>
    <bndbox>
      <xmin>1126.0</xmin>
      <ymin>355.0</ymin>
      <xmax>1158.0</xmax>
      <ymax>446.0</ymax>
    </bndbox>
  </object>
  <object>
    <name>16_-3</name>
    <difficult>0</difficult>
    <bndbox>
      <xmin>1172.0</xmin>
      <ymin>347.0</ymin>
      <xmax>1200.0</xmax>
      <ymax>463.0</ymax>
    </bndbox>
  </object>
  <object>
    <name>16_4</name>
    <difficult>0</difficult>
    <bndbox>
      <xmin>1225.0</xmin>
      <ymin>335.0</ymin>
      <xmax>1252.0</xmax>
      <ymax>429.0</ymax>
    </bndbox>
  </object>
  <object>
    <name>16_5</name>
    <difficult>0</difficult>
    <bndbox>
      <xmin>1277.0</xmin>
      <ymin>325.0</ymin>
      <xmax>1304.0</xmax>
      <ymax>430.0</ymax>
    </bndbox>
  </object>
  <object>
    <name>16_6</name>
    <difficult>0</difficult>
    <bndbox>
      <xmin>1328.0</xmin>
      <ymin>357.0</ymin>
      <xmax>1354.0</xmax>
      <ymax>451.0</ymax>
    </bndbox>
  </object>
  <object>
    <name>16_5</name>
    <difficult>0</difficult>
    <bndbox>
      <xmin>1378.0</xmin>
      <ymin>358.0</ymin>
      <xmax>1404.0</xmax>
      <ymax>456.0</ymax>
    </bndbox>
  </object>
  <object>
    <name>16_4</name>
    <difficult>0</difficult>
    <bndbox>
      <xmin>1428.0</xmin>
      <ymin>358.0</ymin>
      <xmax>1454.0</xmax>
      <ymax>461.0</ymax>
    </bndbox>
  </object>
  <object>
    <name>16_3</name>
    <difficult>0</difficult>
    <bndbox>
      <xmin>1471.0</xmin>
      <ymin>357.0</ymin>
      <xmax>1505.0</xmax>
      <ymax>463.0</ymax>
    </bndbox>
  </object>
  <object>
    <name>16_2</name>
    <difficult>0</difficult>
    <bndbox>
      <xmin>1530.0</xmin>
      <ymin>340.0</ymin>
      <xmax>1562.0</xmax>
      <ymax>430.0</ymax>
    </bndbox>
  </object>
  <object>
    <name>16_1</name>
    <difficult>0</difficult>
    <bndbox>
      <xmin>1578.0</xmin>
      <ymin>338.0</ymin>
      <xmax>1606.0</xmax>
      <ymax>431.0</ymax>
    </bndbox>
  </object>
  <object>
    <name>16_0</name>
    <difficult>0</difficult>
    <bndbox>
      <xmin>1629.0</xmin>
      <ymin>334.0</ymin>
      <xmax>1656.0</xmax>
      <ymax>439.0</ymax>
    </bndbox>
  </object>
  <object>
    <name>16_4</name>
    <difficult>0</difficult>
    <bndbox>
      <xmin>1731.0</xmin>
      <ymin>330.0</ymin>
      <xmax>1757.0</xmax>
      <ymax>430.0</ymax>
    </bndbox>
  </object>
  <object>
    <name>16_3</name>
    <difficult>0</difficult>
    <bndbox>
      <xmin>1781.0</xmin>
      <ymin>338.0</ymin>
      <xmax>1816.0</xmax>
      <ymax>429.0</ymax>
    </bndbox>
  </object>
  <object>
    <name>16_4</name>
    <difficult>0</difficult>
    <bndbox>
      <xmin>1834.0</xmin>
      <ymin>339.0</ymin>
      <xmax>1861.0</xmax>
      <ymax>430.0</ymax>
    </bndbox>
  </object>
  <object>
    <name>16_3</name>
    <difficult>0</difficult>
    <bndbox>
      <xmin>1884.0</xmin>
      <ymin>340.0</ymin>
      <xmax>1911.0</xmax>
      <ymax>430.0</ymax>
    </bndbox>
  </object>
  <object>
    <name>16_2</name>
    <difficult>0</difficult>
    <bndbox>
      <xmin>1934.0</xmin>
      <ymin>340.0</ymin>
      <xmax>1961.0</xmax>
      <ymax>431.0</ymax>
    </bndbox>
  </object>
  <object>
    <name>8_1</name>
    <difficult>0</difficult>
    <bndbox>
      <xmin>2016.0</xmin>
      <ymin>337.0</ymin>
      <xmax>2049.0</xmax>
      <ymax>431.0</ymax>
    </bndbox>
  </object>
  <object>
    <name>8_8</name>
    <difficult>0</difficult>
    <bndbox>
      <xmin>2116.0</xmin>
      <ymin>308.0</ymin>
      <xmax>2143.0</xmax>
      <ymax>430.0</ymax>
    </bndbox>
  </object>
  <object>
    <name>4_7</name>
    <difficult>0</difficult>
    <bndbox>
      <xmin>2218.0</xmin>
      <ymin>358.0</ymin>
      <xmax>2244.0</xmax>
      <ymax>429.0</ymax>
    </bndbox>
  </object>
  <object>
    <name>Rests8</name>
    <difficult>0</difficult>
    <bndbox>
      <xmin>2420.0</xmin>
      <ymin>344.0</ymin>
      <xmax>2443.0</xmax>
      <ymax>377.0</ymax>
    </bndbox>
  </object>
  <object>
    <name>8_6</name>
    <difficult>0</difficult>
    <bndbox>
      <xmin>2524.0</xmin>
      <ymin>358.0</ymin>
      <xmax>2549.0</xmax>
      <ymax>435.0</ymax>
    </bndbox>
  </object>
  <object>
    <name>4_8</name>
    <difficult>0</difficult>
    <bndbox>
      <xmin>2625.0</xmin>
      <ymin>350.0</ymin>
      <xmax>2649.0</xmax>
      <ymax>430.0</ymax>
    </bndbox>
  </object>
  <object>
    <name>mp</name>
    <difficult>0</difficult>
    <bndbox>
      <xmin>269.0</xmin>
      <ymin>449.0</ymin>
      <xmax>332.0</xmax>
      <ymax>488.0</ymax>
    </bndbox>
  </object>
  <object>
    <name>mf</name>
    <difficult>0</difficult>
    <bndbox>
      <xmin>2103.0</xmin>
      <ymin>438.0</ymin>
      <xmax>2162.0</xmax>
      <ymax>483.0</ymax>
    </bndbox>
  </object>
  <object>
    <name>Vla</name>
    <difficult>0</difficult>
    <bndbox>
      <xmin>23.0</xmin>
      <ymin>587.0</ymin>
      <xmax>84.0</xmax>
      <ymax>629.0</ymax>
    </bndbox>
  </object>
  <object>
    <name>Gclef</name>
    <difficult>0</difficult>
    <bndbox>
      <xmin>154.0</xmin>
      <ymin>538.0</ymin>
      <xmax>204.0</xmax>
      <ymax>668.0</ymax>
    </bndbox>
  </object>
  <object>
    <name>16_6</name>
    <difficult>0</difficult>
    <bndbox>
      <xmin>289.0</xmin>
      <ymin>536.0</ymin>
      <xmax>322.0</xmax>
      <ymax>642.0</ymax>
    </bndbox>
  </object>
  <object>
    <name>16_5</name>
    <difficult>0</difficult>
    <bndbox>
      <xmin>339.0</xmin>
      <ymin>536.0</ymin>
      <xmax>366.0</xmax>
      <ymax>643.0</ymax>
    </bndbox>
  </object>
  <object>
    <name>16_6</name>
    <difficult>0</difficult>
    <bndbox>
      <xmin>390.0</xmin>
      <ymin>537.0</ymin>
      <xmax>415.0</xmax>
      <ymax>642.0</ymax>
    </bndbox>
  </object>
  <object>
    <name>16_-1</name>
    <difficult>0</difficult>
    <bndbox>
      <xmin>437.0</xmin>
      <ymin>537.0</ymin>
      <xmax>465.0</xmax>
      <ymax>661.0</ymax>
    </bndbox>
  </object>
  <object>
    <name>16_-2</name>
    <difficult>0</difficult>
    <bndbox>
      <xmin>487.0</xmin>
      <ymin>569.0</ymin>
      <xmax>522.0</xmax>
      <ymax>667.0</ymax>
    </bndbox>
  </object>
  <object>
    <name>16_3</name>
    <difficult>0</difficult>
    <bndbox>
      <xmin>539.0</xmin>
      <ymin>570.0</ymin>
      <xmax>564.0</xmax>
      <ymax>642.0</ymax>
    </bndbox>
  </object>
  <object>
    <name>16_0</name>
    <difficult>0</difficult>
    <bndbox>
      <xmin>589.0</xmin>
      <ymin>569.0</ymin>
      <xmax>615.0</xmax>
      <ymax>652.0</ymax>
    </bndbox>
  </object>
  <object>
    <name>16_1</name>
    <difficult>0</difficult>
    <bndbox>
      <xmin>638.0</xmin>
      <ymin>570.0</ymin>
      <xmax>664.0</xmax>
      <ymax>644.0</ymax>
    </bndbox>
  </object>
  <object>
    <name>16_-1</name>
    <difficult>0</difficult>
    <bndbox>
      <xmin>686.0</xmin>
      <ymin>541.0</ymin>
      <xmax>722.0</xmax>
      <ymax>660.0</ymax>
    </bndbox>
  </object>
  <object>
    <name>16_6</name>
    <difficult>0</difficult>
    <bndbox>
      <xmin>742.0</xmin>
      <ymin>542.0</ymin>
      <xmax>768.0</xmax>
      <ymax>643.0</ymax>
    </bndbox>
  </object>
  <object>
    <name>16_5</name>
    <difficult>0</difficult>
    <bndbox>
      <xmin>792.0</xmin>
      <ymin>542.0</ymin>
      <xmax>818.0</xmax>
      <ymax>643.0</ymax>
    </bndbox>
  </object>
  <object>
    <name>16_4</name>
    <difficult>0</difficult>
    <bndbox>
      <xmin>843.0</xmin>
      <ymin>542.0</ymin>
      <xmax>868.0</xmax>
      <ymax>643.0</ymax>
    </bndbox>
  </object>
  <object>
    <name>16_5</name>
    <difficult>0</difficult>
    <bndbox>
      <xmin>892.0</xmin>
      <ymin>570.0</ymin>
      <xmax>918.0</xmax>
      <ymax>659.0</ymax>
    </bndbox>
  </object>
  <object>
    <name>16_8</name>
    <difficult>0</difficult>
    <bndbox>
      <xmin>945.0</xmin>
      <ymin>563.0</ymin>
      <xmax>969.0</xmax>
      <ymax>649.0</ymax>
    </bndbox>
  </object>
  <object>
    <name>16_10</name>
    <difficult>0</difficult>
    <bndbox>
      <xmin>996.0</xmin>
      <ymin>546.0</ymin>
      <xmax>1025.0</xmax>
      <ymax>643.0</ymax>
    </bndbox>
  </object>
  <object>
    <name>16_11</name>
    <difficult>0</difficult>
    <bndbox>
      <xmin>1040.0</xmin>
      <ymin>539.0</ymin>
      <xmax>1074.0</xmax>
      <ymax>644.0</ymax>
    </bndbox>
  </object>
  <object>
    <name>16_9</name>
    <difficult>0</difficult>
    <bndbox>
      <xmin>1124.0</xmin>
      <ymin>553.0</ymin>
      <xmax>1149.0</xmax>
      <ymax>643.0</ymax>
    </bndbox>
  </object>
  <object>
    <name>16_8</name>
    <difficult>0</difficult>
    <bndbox>
      <xmin>1172.0</xmin>
      <ymin>563.0</ymin>
      <xmax>1197.0</xmax>
      <ymax>643.0</ymax>
    </bndbox>
  </object>
  <object>
    <name>16_7</name>
    <difficult>0</difficult>
    <bndbox>
      <xmin>1224.0</xmin>
      <ymin>570.0</ymin>
      <xmax>1250.0</xmax>
      <ymax>644.0</ymax>
    </bndbox>
  </object>
  <object>
    <name>16_9</name>
    <difficult>0</difficult>
    <bndbox>
      <xmin>1269.0</xmin>
      <ymin>554.0</ymin>
      <xmax>1301.0</xmax>
      <ymax>643.0</ymax>
    </bndbox>
  </object>
  <object>
    <name>16_8</name>
    <difficult>0</difficult>
    <bndbox>
      <xmin>1328.0</xmin>
      <ymin>563.0</ymin>
      <xmax>1353.0</xmax>
      <ymax>647.0</ymax>
    </bndbox>
  </object>
  <object>
    <name>16_7</name>
    <difficult>0</difficult>
    <bndbox>
      <xmin>1377.0</xmin>
      <ymin>570.0</ymin>
      <xmax>1403.0</xmax>
      <ymax>651.0</ymax>
    </bndbox>
  </object>
  <object>
    <name>16_6</name>
    <difficult>0</difficult>
    <bndbox>
      <xmin>1428.0</xmin>
      <ymin>570.0</ymin>
      <xmax>1453.0</xmax>
      <ymax>655.0</ymax>
    </bndbox>
  </object>
  <object>
    <name>16_5</name>
    <difficult>0</difficult>
    <bndbox>
      <xmin>1471.0</xmin>
      <ymin>570.0</ymin>
      <xmax>1505.0</xmax>
      <ymax>659.0</ymax>
    </bndbox>
  </object>
  <object>
    <name>16_4</name>
    <difficult>0</difficult>
    <bndbox>
      <xmin>1530.0</xmin>
      <ymin>550.0</ymin>
      <xmax>1562.0</xmax>
      <ymax>644.0</ymax>
    </bndbox>
  </object>
  <object>
    <name>16_3</name>
    <difficult>0</difficult>
    <bndbox>
      <xmin>1580.0</xmin>
      <ymin>546.0</ymin>
      <xmax>1606.0</xmax>
      <ymax>643.0</ymax>
    </bndbox>
  </object>
  <object>
    <name>16_2</name>
    <difficult>0</difficult>
    <bndbox>
      <xmin>1630.0</xmin>
      <ymin>543.0</ymin>
      <xmax>1656.0</xmax>
      <ymax>643.0</ymax>
    </bndbox>
  </object>
  <object>
    <name>Cclef</name>
    <difficult>0</difficult>
    <bndbox>
      <xmin>1670.0</xmin>
      <ymin>570.0</ymin>
      <xmax>1711.0</xmax>
      <ymax>641.0</ymax>
    </bndbox>
  </object>
  <object>
    <name>16_7</name>
    <difficult>0</difficult>
    <bndbox>
      <xmin>1731.0</xmin>
      <ymin>533.0</ymin>
      <xmax>1758.0</xmax>
      <ymax>643.0</ymax>
    </bndbox>
  </object>
  <object>
    <name>16_6</name>
    <difficult>0</difficult>
    <bndbox>
      <xmin>1781.0</xmin>
      <ymin>570.0</ymin>
      <xmax>1807.0</xmax>
      <ymax>647.0</ymax>
    </bndbox>
  </object>
  <object>
    <name>16_8</name>
    <difficult>0</difficult>
    <bndbox>
      <xmin>1833.0</xmin>
      <ymin>563.0</ymin>
      <xmax>1858.0</xmax>
      <ymax>647.0</ymax>
    </bndbox>
  </object>
  <object>
    <name>16_7</name>
    <difficult>0</difficult>
    <bndbox>
      <xmin>1883.0</xmin>
      <ymin>570.0</ymin>
      <xmax>1909.0</xmax>
      <ymax>647.0</ymax>
    </bndbox>
  </object>
  <object>
    <name>16_6</name>
    <difficult>0</difficult>
    <bndbox>
      <xmin>1927.0</xmin>
      <ymin>570.0</ymin>
      <xmax>1959.0</xmax>
      <ymax>647.0</ymax>
    </bndbox>
  </object>
  <object>
    <name>16_5</name>
    <difficult>0</difficult>
    <bndbox>
      <xmin>2016.0</xmin>
      <ymin>570.0</ymin>
      <xmax>2041.0</xmax>
      <ymax>656.0</ymax>
    </bndbox>
  </object>
  <object>
    <name>16_6</name>
    <difficult>0</difficult>
    <bndbox>
      <xmin>2067.0</xmin>
      <ymin>569.0</ymin>
      <xmax>2091.0</xmax>
      <ymax>654.0</ymax>
    </bndbox>
  </object>
  <object>
    <name>16_7</name>
    <difficult>0</difficult>
    <bndbox>
      <xmin>2116.0</xmin>
      <ymin>569.0</ymin>
      <xmax>2142.0</xmax>
      <ymax>651.0</ymax>
    </bndbox>
  </object>
  <object>
    <name>16_8</name>
    <difficult>0</difficult>
    <bndbox>
      <xmin>2159.0</xmin>
      <ymin>563.0</ymin>
      <xmax>2191.0</xmax>
      <ymax>646.0</ymax>
    </bndbox>
  </object>
  <object>
    <name>16_9</name>
    <difficult>0</difficult>
    <bndbox>
      <xmin>2218.0</xmin>
      <ymin>554.0</ymin>
      <xmax>2242.0</xmax>
      <ymax>644.0</ymax>
    </bndbox>
  </object>
  <object>
    <name>16_6</name>
    <difficult>0</difficult>
    <bndbox>
      <xmin>2264.0</xmin>
      <ymin>570.0</ymin>
      <xmax>2289.0</xmax>
      <ymax>643.0</ymax>
    </bndbox>
  </object>
  <object>
    <name>16_9</name>
    <difficult>0</difficult>
    <bndbox>
      <xmin>2318.0</xmin>
      <ymin>554.0</ymin>
      <xmax>2343.0</xmax>
      <ymax>643.0</ymax>
    </bndbox>
  </object>
  <object>
    <name>16_8</name>
    <difficult>0</difficult>
    <bndbox>
      <xmin>2360.0</xmin>
      <ymin>563.0</ymin>
      <xmax>2393.0</xmax>
      <ymax>644.0</ymax>
    </bndbox>
  </object>
  <object>
    <name>16_7</name>
    <difficult>0</difficult>
    <bndbox>
      <xmin>2419.0</xmin>
      <ymin>570.0</ymin>
      <xmax>2444.0</xmax>
      <ymax>643.0</ymax>
    </bndbox>
  </object>
  <object>
    <name>16_10</name>
    <difficult>0</difficult>
    <bndbox>
      <xmin>2472.0</xmin>
      <ymin>546.0</ymin>
      <xmax>2502.0</xmax>
      <ymax>643.0</ymax>
    </bndbox>
  </object>
  <object>
    <name>16_9</name>
    <difficult>0</difficult>
    <bndbox>
      <xmin>2523.0</xmin>
      <ymin>554.0</ymin>
      <xmax>2548.0</xmax>
      <ymax>642.0</ymax>
    </bndbox>
  </object>
  <object>
    <name>16_8</name>
    <difficult>0</difficult>
    <bndbox>
      <xmin>2567.0</xmin>
      <ymin>563.0</ymin>
      <xmax>2598.0</xmax>
      <ymax>642.0</ymax>
    </bndbox>
  </object>
  <object>
    <name>16_9</name>
    <difficult>0</difficult>
    <bndbox>
      <xmin>2624.0</xmin>
      <ymin>554.0</ymin>
      <xmax>2649.0</xmax>
      <ymax>643.0</ymax>
    </bndbox>
  </object>
  <object>
    <name>16_8</name>
    <difficult>0</difficult>
    <bndbox>
      <xmin>2674.0</xmin>
      <ymin>563.0</ymin>
      <xmax>2699.0</xmax>
      <ymax>643.0</ymax>
    </bndbox>
  </object>
  <object>
    <name>16_7</name>
    <difficult>0</difficult>
    <bndbox>
      <xmin>2724.0</xmin>
      <ymin>569.0</ymin>
      <xmax>2750.0</xmax>
      <ymax>643.0</ymax>
    </bndbox>
  </object>
  <object>
    <name>16_6</name>
    <difficult>0</difficult>
    <bndbox>
      <xmin>2768.0</xmin>
      <ymin>570.0</ymin>
      <xmax>2799.0</xmax>
      <ymax>643.0</ymax>
    </bndbox>
  </object>
  <object>
    <name>mf</name>
    <difficult>0</difficult>
    <bndbox>
      <xmin>273.0</xmin>
      <ymin>651.0</ymin>
      <xmax>331.0</xmax>
      <ymax>693.0</ymax>
    </bndbox>
  </object>
  <object>
    <name>mp</name>
    <difficult>0</difficult>
    <bndbox>
      <xmin>1997.0</xmin>
      <ymin>662.0</ymin>
      <xmax>2057.0</xmax>
      <ymax>697.0</ymax>
    </bndbox>
  </object>
  <object>
    <name>Vlc</name>
    <difficult>0</difficult>
    <bndbox>
      <xmin>27.0</xmin>
      <ymin>756.0</ymin>
      <xmax>87.0</xmax>
      <ymax>798.0</ymax>
    </bndbox>
  </object>
  <object>
    <name>Fclef</name>
    <difficult>0</difficult>
    <bndbox>
      <xmin>152.0</xmin>
      <ymin>741.0</ymin>
      <xmax>203.0</xmax>
      <ymax>814.0</ymax>
    </bndbox>
  </object>
  <object>
    <name>4_4</name>
    <difficult>0</difficult>
    <bndbox>
      <xmin>288.0</xmin>
      <ymin>741.0</ymin>
      <xmax>314.0</xmax>
      <ymax>833.0</ymax>
    </bndbox>
  </object>
  <object>
    <name>4_1</name>
    <difficult>0</difficult>
    <bndbox>
      <xmin>488.0</xmin>
      <ymin>742.0</ymin>
      <xmax>514.0</xmax>
      <ymax>813.0</ymax>
    </bndbox>
  </object>
  <object>
    <name>4_2</name>
    <difficult>0</difficult>
    <bndbox>
      <xmin>688.0</xmin>
      <ymin>732.0</ymin>
      <xmax>715.0</xmax>
      <ymax>815.0</ymax>
    </bndbox>
  </object>
  <object>
    <name>4_-1</name>
    <difficult>0</difficult>
    <bndbox>
      <xmin>892.0</xmin>
      <ymin>740.0</ymin>
      <xmax>919.0</xmax>
      <ymax>829.0</ymax>
    </bndbox>
  </object>
  <object>
    <name>4_0</name>
    <difficult>0</difficult>
    <bndbox>
      <xmin>1126.0</xmin>
      <ymin>741.0</ymin>
      <xmax>1151.0</xmax>
      <ymax>821.0</ymax>
    </bndbox>
  </object>
  <object>
    <name>4_-3</name>
    <difficult>0</difficult>
    <bndbox>
      <xmin>1326.0</xmin>
      <ymin>740.0</ymin>
      <xmax>1356.0</xmax>
      <ymax>845.0</ymax>
    </bndbox>
  </object>
  <object>
    <name>4_0</name>
    <difficult>0</difficult>
    <bndbox>
      <xmin>1531.0</xmin>
      <ymin>741.0</ymin>
      <xmax>1555.0</xmax>
      <ymax>821.0</ymax>
    </bndbox>
  </object>
  <object>
    <name>4_1</name>
    <difficult>0</difficult>
    <bndbox>
      <xmin>1781.0</xmin>
      <ymin>742.0</ymin>
      <xmax>1808.0</xmax>
      <ymax>813.0</ymax>
    </bndbox>
  </object>
  <object>
    <name>4_4</name>
    <difficult>0</difficult>
    <bndbox>
      <xmin>2016.0</xmin>
      <ymin>742.0</ymin>
      <xmax>2042.0</xmax>
      <ymax>834.0</ymax>
    </bndbox>
  </object>
  <object>
    <name>4_1</name>
    <difficult>0</difficult>
    <bndbox>
      <xmin>2218.0</xmin>
      <ymin>742.0</ymin>
      <xmax>2245.0</xmax>
      <ymax>813.0</ymax>
    </bndbox>
  </object>
  <object>
    <name>4_2</name>
    <difficult>0</difficult>
    <bndbox>
      <xmin>2421.0</xmin>
      <ymin>733.0</ymin>
      <xmax>2448.0</xmax>
      <ymax>813.0</ymax>
    </bndbox>
  </object>
  <object>
    <name>4_-1</name>
    <difficult>0</difficult>
    <bndbox>
      <xmin>2625.0</xmin>
      <ymin>740.0</ymin>
      <xmax>2651.0</xmax>
      <ymax>828.0</ymax>
    </bndbox>
  </object>
  <object>
    <name>Gclef</name>
    <difficult>0</difficult>
    <bndbox>
      <xmin>155.0</xmin>
      <ymin>922.0</ymin>
      <xmax>202.0</xmax>
      <ymax>1050.0</ymax>
    </bndbox>
  </object>
  <object>
    <name>Fclef</name>
    <difficult>0</difficult>
    <bndbox>
      <xmin>152.0</xmin>
      <ymin>1124.0</ymin>
      <xmax>203.0</xmax>
      <ymax>1196.0</ymax>
    </bndbox>
  </object>
  <object>
    <name>4_4</name>
    <difficult>0</difficult>
    <bndbox>
      <xmin>289.0</xmin>
      <ymin>1123.0</ymin>
      <xmax>315.0</xmax>
      <ymax>1215.0</ymax>
    </bndbox>
  </object>
  <object>
    <name>4_1</name>
    <difficult>0</difficult>
    <bndbox>
      <xmin>488.0</xmin>
      <ymin>1125.0</ymin>
      <xmax>514.0</xmax>
      <ymax>1196.0</ymax>
    </bndbox>
  </object>
  <object>
    <name>4_2</name>
    <difficult>0</difficult>
    <bndbox>
      <xmin>689.0</xmin>
      <ymin>1116.0</ymin>
      <xmax>716.0</xmax>
      <ymax>1196.0</ymax>
    </bndbox>
  </object>
  <object>
    <name>4_-1</name>
    <difficult>0</difficult>
    <bndbox>
      <xmin>892.0</xmin>
      <ymin>1124.0</ymin>
      <xmax>920.0</xmax>
      <ymax>1211.0</ymax>
    </bndbox>
  </object>
  <object>
    <name>4_0</name>
    <difficult>0</difficult>
    <bndbox>
      <xmin>1125.0</xmin>
      <ymin>1124.0</ymin>
      <xmax>1152.0</xmax>
      <ymax>1204.0</ymax>
    </bndbox>
  </object>
  <object>
    <name>4_-3</name>
    <difficult>0</difficult>
    <bndbox>
      <xmin>1326.0</xmin>
      <ymin>1123.0</ymin>
      <xmax>1356.0</xmax>
      <ymax>1229.0</ymax>
    </bndbox>
  </object>
  <object>
    <name>4_0</name>
    <difficult>0</difficult>
    <bndbox>
      <xmin>1529.0</xmin>
      <ymin>1124.0</ymin>
      <xmax>1556.0</xmax>
      <ymax>1205.0</ymax>
    </bndbox>
  </object>
  <object>
    <name>4_1</name>
    <difficult>0</difficult>
    <bndbox>
      <xmin>1781.0</xmin>
      <ymin>1126.0</ymin>
      <xmax>1808.0</xmax>
      <ymax>1196.0</ymax>
    </bndbox>
  </object>
  <object>
    <name>4_4</name>
    <difficult>0</difficult>
    <bndbox>
      <xmin>2017.0</xmin>
      <ymin>1123.0</ymin>
      <xmax>2043.0</xmax>
      <ymax>1216.0</ymax>
    </bndbox>
  </object>
  <object>
    <name>4_1</name>
    <difficult>0</difficult>
    <bndbox>
      <xmin>2218.0</xmin>
      <ymin>1126.0</ymin>
      <xmax>2245.0</xmax>
      <ymax>1196.0</ymax>
    </bndbox>
  </object>
  <object>
    <name>4_2</name>
    <difficult>0</difficult>
    <bndbox>
      <xmin>2421.0</xmin>
      <ymin>1116.0</ymin>
      <xmax>2448.0</xmax>
      <ymax>1196.0</ymax>
    </bndbox>
  </object>
  <object>
    <name>4_-1</name>
    <difficult>0</difficult>
    <bndbox>
      <xmin>2625.0</xmin>
      <ymin>1123.0</ymin>
      <xmax>2652.0</xmax>
      <ymax>1211.0</ymax>
    </bndbox>
  </object>
  <object>
    <name>Gclef</name>
    <difficult>0</difficult>
    <bndbox>
      <xmin>156.0</xmin>
      <ymin>1552.0</ymin>
      <xmax>202.0</xmax>
      <ymax>1679.0</ymax>
    </bndbox>
  </object>
  <object>
    <name>4_6</name>
    <difficult>0</difficult>
    <bndbox>
      <xmin>289.0</xmin>
      <ymin>1582.0</ymin>
      <xmax>314.0</xmax>
      <ymax>1663.0</ymax>
    </bndbox>
  </object>
  <object>
    <name>8_6</name>
    <difficult>0</difficult>
    <bndbox>
      <xmin>715.0</xmin>
      <ymin>1582.0</ymin>
      <xmax>740.0</xmax>
      <ymax>1659.0</ymax>
    </bndbox>
  </object>
  <object>
    <name>8_6</name>
    <difficult>0</difficult>
    <bndbox>
      <xmin>857.0</xmin>
      <ymin>1582.0</ymin>
      <xmax>882.0</xmax>
      <ymax>1658.0</ymax>
    </bndbox>
  </object>
  <object>
    <name>8_9</name>
    <difficult>0</difficult>
    <bndbox>
      <xmin>991.0</xmin>
      <ymin>1567.0</ymin>
      <xmax>1024.0</xmax>
      <ymax>1655.0</ymax>
    </bndbox>
  </object>
  <object>
    <name>8_7</name>
    <difficult>0</difficult>
    <bndbox>
      <xmin>1145.0</xmin>
      <ymin>1582.0</ymin>
      <xmax>1171.0</xmax>
      <ymax>1652.0</ymax>
    </bndbox>
  </object>
  <object>
    <name>8_10</name>
    <difficult>0</difficult>
    <bndbox>
      <xmin>1279.0</xmin>
      <ymin>1559.0</ymin>
      <xmax>1313.0</xmax>
      <ymax>1654.0</ymax>
    </bndbox>
  </object>
  <object>
    <name>16_10</name>
    <difficult>0</difficult>
    <bndbox>
      <xmin>1461.0</xmin>
      <ymin>1559.0</ymin>
      <xmax>1490.0</xmax>
      <ymax>1655.0</ymax>
    </bndbox>
  </object>
  <object>
    <name>mf</name>
    <difficult>0</difficult>
    <bndbox>
      <xmin>1447.0</xmin>
      <ymin>1661.0</ymin>
      <xmax>1505.0</xmax>
      <ymax>1704.0</ymax>
    </bndbox>
  </object>
  <object>
    <name>32_8</name>
    <difficult>0</difficult>
    <bndbox>
      <xmin>1528.0</xmin>
      <ymin>1575.0</ymin>
      <xmax>1556.0</xmax>
      <ymax>1656.0</ymax>
    </bndbox>
  </object>
  <object>
    <name>32_9</name>
    <difficult>0</difficult>
    <bndbox>
      <xmin>1567.0</xmin>
      <ymin>1567.0</ymin>
      <xmax>1600.0</xmax>
      <ymax>1654.0</ymax>
    </bndbox>
  </object>
  <object>
    <name>16_10</name>
    <difficult>0</difficult>
    <bndbox>
      <xmin>1619.0</xmin>
      <ymin>1559.0</ymin>
      <xmax>1649.0</xmax>
      <ymax>1655.0</ymax>
    </bndbox>
  </object>
  <object>
    <name>32_8</name>
    <difficult>0</difficult>
    <bndbox>
      <xmin>1686.0</xmin>
      <ymin>1574.0</ymin>
      <xmax>1714.0</xmax>
      <ymax>1655.0</ymax>
    </bndbox>
  </object>
  <object>
    <name>32_9</name>
    <difficult>0</difficult>
    <bndbox>
      <xmin>1726.0</xmin>
      <ymin>1567.0</ymin>
      <xmax>1757.0</xmax>
      <ymax>1655.0</ymax>
    </bndbox>
  </object>
  <object>
    <name>32_10</name>
    <difficult>0</difficult>
    <bndbox>
      <xmin>1776.0</xmin>
      <ymin>1559.0</ymin>
      <xmax>1808.0</xmax>
      <ymax>1689.0</ymax>
    </bndbox>
  </object>
  <object>
    <name>32_3</name>
    <difficult>0</difficult>
    <bndbox>
      <xmin>1820.0</xmin>
      <ymin>1582.0</ymin>
      <xmax>1846.0</xmax>
      <ymax>1688.0</ymax>
    </bndbox>
  </object>
  <object>
    <name>32_4</name>
    <difficult>0</difficult>
    <bndbox>
      <xmin>1866.0</xmin>
      <ymin>1580.0</ymin>
      <xmax>1892.0</xmax>
      <ymax>1686.0</ymax>
    </bndbox>
  </object>
  <object>
    <name>32_5</name>
    <difficult>0</difficult>
    <bndbox>
      <xmin>1911.0</xmin>
      <ymin>1581.0</ymin>
      <xmax>1937.0</xmax>
      <ymax>1688.0</ymax>
    </bndbox>
  </object>
  <object>
    <name>32_6</name>
    <difficult>0</difficult>
    <bndbox>
      <xmin>1957.0</xmin>
      <ymin>1580.0</ymin>
      <xmax>1983.0</xmax>
      <ymax>1688.0</ymax>
    </bndbox>
  </object>
  <object>
    <name>32_7</name>
    <difficult>0</difficult>
    <bndbox>
      <xmin>2003.0</xmin>
      <ymin>1582.0</ymin>
      <xmax>2027.0</xmax>
      <ymax>1688.0</ymax>
    </bndbox>
  </object>
  <object>
    <name>32_8</name>
    <difficult>0</difficult>
    <bndbox>
      <xmin>2049.0</xmin>
      <ymin>1575.0</ymin>
      <xmax>2072.0</xmax>
      <ymax>1689.0</ymax>
    </bndbox>
  </object>
  <object>
    <name>32_9</name>
    <difficult>0</difficult>
    <bndbox>
      <xmin>2085.0</xmin>
      <ymin>1565.0</ymin>
      <xmax>2119.0</xmax>
      <ymax>1689.0</ymax>
    </bndbox>
  </object>
  <object>
    <name>16_8</name>
    <difficult>0</difficult>
    <bndbox>
      <xmin>2140.0</xmin>
      <ymin>1574.0</ymin>
      <xmax>2164.0</xmax>
      <ymax>1673.0</ymax>
    </bndbox>
  </object>
  <object>
    <name>32_6</name>
    <difficult>0</difficult>
    <bndbox>
      <xmin>2207.0</xmin>
      <ymin>1581.0</ymin>
      <xmax>2232.0</xmax>
      <ymax>1671.0</ymax>
    </bndbox>
  </object>
  <object>
    <name>32_7</name>
    <difficult>0</difficult>
    <bndbox>
      <xmin>2243.0</xmin>
      <ymin>1583.0</ymin>
      <xmax>2276.0</xmax>
      <ymax>1671.0</ymax>
    </bndbox>
  </object>
  <object>
    <name>16_8</name>
    <difficult>0</difficult>
    <bndbox>
      <xmin>2298.0</xmin>
      <ymin>1575.0</ymin>
      <xmax>2324.0</xmax>
      <ymax>1705.0</ymax>
    </bndbox>
  </object>
  <object>
    <name>32_1</name>
    <difficult>0</difficult>
    <bndbox>
      <xmin>2364.0</xmin>
      <ymin>1579.0</ymin>
      <xmax>2391.0</xmax>
      <ymax>1704.0</ymax>
    </bndbox>
  </object>
  <object>
    <name>32_2</name>
    <difficult>0</difficult>
    <bndbox>
      <xmin>2400.0</xmin>
      <ymin>1579.0</ymin>
      <xmax>2437.0</xmax>
      <ymax>1703.0</ymax>
    </bndbox>
  </object>
  <object>
    <name>32_3</name>
    <difficult>0</difficult>
    <bndbox>
      <xmin>2456.0</xmin>
      <ymin>1553.0</ymin>
      <xmax>2489.0</xmax>
      <ymax>1654.0</ymax>
    </bndbox>
  </object>
  <object>
    <name>32_4</name>
    <difficult>0</difficult>
    <bndbox>
      <xmin>2503.0</xmin>
      <ymin>1554.0</ymin>
      <xmax>2527.0</xmax>
      <ymax>1655.0</ymax>
    </bndbox>
  </object>
  <object>
    <name>32_3</name>
    <difficult>0</difficult>
    <bndbox>
      <xmin>2547.0</xmin>
      <ymin>1554.0</ymin>
      <xmax>2573.0</xmax>
      <ymax>1654.0</ymax>
    </bndbox>
  </object>
  <object>
    <name>32_2</name>
    <difficult>0</difficult>
    <bndbox>
      <xmin>2594.0</xmin>
      <ymin>1553.0</ymin>
      <xmax>2619.0</xmax>
      <ymax>1654.0</ymax>
    </bndbox>
  </object>
  <object>
    <name>32_3</name>
    <difficult>0</difficult>
    <bndbox>
      <xmin>2639.0</xmin>
      <ymin>1553.0</ymin>
      <xmax>2664.0</xmax>
      <ymax>1654.0</ymax>
    </bndbox>
  </object>
  <object>
    <name>16_1</name>
    <difficult>0</difficult>
    <bndbox>
      <xmin>2683.0</xmin>
      <ymin>1553.0</ymin>
      <xmax>2708.0</xmax>
      <ymax>1656.0</ymax>
    </bndbox>
  </object>
  <object>
    <name>32_2</name>
    <difficult>0</difficult>
    <bndbox>
      <xmin>2730.0</xmin>
      <ymin>1553.0</ymin>
      <xmax>2755.0</xmax>
      <ymax>1655.0</ymax>
    </bndbox>
  </object>
  <object>
    <name>32_3</name>
    <difficult>0</difficult>
    <bndbox>
      <xmin>2775.0</xmin>
      <ymin>1553.0</ymin>
      <xmax>2799.0</xmax>
      <ymax>1654.0</ymax>
    </bndbox>
  </object>
  <object>
    <name>Vln</name>
    <difficult>0</difficult>
    <bndbox>
      <xmin>1.0</xmin>
      <ymin>1781.0</ymin>
      <xmax>54.0</xmax>
      <ymax>1824.0</ymax>
    </bndbox>
  </object>
  <object>
    <name>Gclef</name>
    <difficult>0</difficult>
    <bndbox>
      <xmin>154.0</xmin>
      <ymin>1736.0</ymin>
      <xmax>203.0</xmax>
      <ymax>1866.0</ymax>
    </bndbox>
  </object>
  <object>
    <name>4_11</name>
    <difficult>0</difficult>
    <bndbox>
      <xmin>287.0</xmin>
      <ymin>1734.0</ymin>
      <xmax>315.0</xmax>
      <ymax>1839.0</ymax>
    </bndbox>
  </object>
  <object>
    <name>4_10</name>
    <difficult>0</difficult>
    <bndbox>
      <xmin>572.0</xmin>
      <ymin>1743.0</ymin>
      <xmax>599.0</xmax>
      <ymax>1840.0</ymax>
    </bndbox>
  </object>
  <object>
    <name>8_11</name>
    <difficult>0</difficult>
    <bndbox>
      <xmin>854.0</xmin>
      <ymin>1734.0</ymin>
      <xmax>884.0</xmax>
      <ymax>1841.0</ymax>
    </bndbox>
  </object>
  <object>
    <name>4_12</name>
    <difficult>0</difficult>
    <bndbox>
      <xmin>1144.0</xmin>
      <ymin>1728.0</ymin>
      <xmax>1173.0</xmax>
      <ymax>1841.0</ymax>
    </bndbox>
  </object>
  <object>
    <name>8_13</name>
    <difficult>0</difficult>
    <bndbox>
      <xmin>1460.0</xmin>
      <ymin>1719.0</ymin>
      <xmax>1488.0</xmax>
      <ymax>1843.0</ymax>
    </bndbox>
  </object>
  <object>
    <name>8_6</name>
    <difficult>0</difficult>
    <bndbox>
      <xmin>1614.0</xmin>
      <ymin>1768.0</ymin>
      <xmax>1645.0</xmax>
      <ymax>1842.0</ymax>
    </bndbox>
  </object>
  <object>
    <name>4_5</name>
    <difficult>0</difficult>
    <bndbox>
      <xmin>1779.0</xmin>
      <ymin>1767.0</ymin>
      <xmax>1803.0</xmax>
      <ymax>1855.0</ymax>
    </bndbox>
  </object>
  <object>
    <name>Rests8</name>
    <difficult>0</difficult>
    <bndbox>
      <xmin>2140.0</xmin>
      <ymin>1753.0</ymin>
      <xmax>2165.0</xmax>
      <ymax>1786.0</ymax>
    </bndbox>
  </object>
  <object>
    <name>8_4</name>
    <difficult>0</difficult>
    <bndbox>
      <xmin>2298.0</xmin>
      <ymin>1767.0</ymin>
      <xmax>2323.0</xmax>
      <ymax>1861.0</ymax>
    </bndbox>
  </object>
  <object>
    <name>4_6</name>
    <difficult>0</difficult>
    <bndbox>
      <xmin>2455.0</xmin>
      <ymin>1767.0</ymin>
      <xmax>2481.0</xmax>
      <ymax>1847.0</ymax>
    </bndbox>
  </object>
  <object>
    <name>mp</name>
    <difficult>0</difficult>
    <bndbox>
      <xmin>1760.0</xmin>
      <ymin>1862.0</ymin>
      <xmax>1820.0</xmax>
      <ymax>1899.0</ymax>
    </bndbox>
  </object>
  <object>
    <name>Vla</name>
    <difficult>0</difficult>
    <bndbox>
      <xmin>22.0</xmin>
      <ymin>1994.0</ymin>
      <xmax>85.0</xmax>
      <ymax>2041.0</ymax>
    </bndbox>
  </object>
  <object>
    <name>Cclef</name>
    <difficult>0</difficult>
    <bndbox>
      <xmin>153.0</xmin>
      <ymin>1981.0</ymin>
      <xmax>205.0</xmax>
      <ymax>2053.0</ymax>
    </bndbox>
  </object>
  <object>
    <name>16_5</name>
    <difficult>0</difficult>
    <bndbox>
      <xmin>289.0</xmin>
      <ymin>1979.0</ymin>
      <xmax>314.0</xmax>
      <ymax>2085.0</ymax>
    </bndbox>
  </object>
  <object>
    <name>16_3</name>
    <difficult>0</difficult>
    <bndbox>
      <xmin>355.0</xmin>
      <ymin>1980.0</ymin>
      <xmax>381.0</xmax>
      <ymax>2076.0</ymax>
    </bndbox>
  </object>
  <object>
    <name>16_10</name>
    <difficult>0</difficult>
    <bndbox>
      <xmin>429.0</xmin>
      <ymin>1956.0</ymin>
      <xmax>458.0</xmax>
      <ymax>2066.0</ymax>
    </bndbox>
  </object>
  <object>
    <name>16_11</name>
    <difficult>0</difficult>
    <bndbox>
      <xmin>491.0</xmin>
      <ymin>1947.0</ymin>
      <xmax>528.0</xmax>
      <ymax>2057.0</ymax>
    </bndbox>
  </object>
  <object>
    <name>16_12</name>
    <difficult>0</difficult>
    <bndbox>
      <xmin>571.0</xmin>
      <ymin>1939.0</ymin>
      <xmax>600.0</xmax>
      <ymax>2053.0</ymax>
    </bndbox>
  </object>
  <object>
    <name>16_11</name>
    <difficult>0</difficult>
    <bndbox>
      <xmin>642.0</xmin>
      <ymin>1947.0</ymin>
      <xmax>669.0</xmax>
      <ymax>2053.0</ymax>
    </bndbox>
  </object>
  <object>
    <name>16_10</name>
    <difficult>0</difficult>
    <bndbox>
      <xmin>713.0</xmin>
      <ymin>1956.0</ymin>
      <xmax>740.0</xmax>
      <ymax>2052.0</ymax>
    </bndbox>
  </object>
  <object>
    <name>16_9</name>
    <difficult>0</difficult>
    <bndbox>
      <xmin>777.0</xmin>
      <ymin>1964.0</ymin>
      <xmax>808.0</xmax>
      <ymax>2052.0</ymax>
    </bndbox>
  </object>
  <object>
    <name>16_8</name>
    <difficult>0</difficult>
    <bndbox>
      <xmin>857.0</xmin>
      <ymin>1973.0</ymin>
      <xmax>881.0</xmax>
      <ymax>2053.0</ymax>
    </bndbox>
  </object>
  <object>
    <name>16_7</name>
    <difficult>0</difficult>
    <bndbox>
      <xmin>927.0</xmin>
      <ymin>1979.0</ymin>
      <xmax>953.0</xmax>
      <ymax>2053.0</ymax>
    </bndbox>
  </object>
  <object>
    <name>16_6</name>
    <difficult>0</difficult>
    <bndbox>
      <xmin>999.0</xmin>
      <ymin>1980.0</ymin>
      <xmax>1024.0</xmax>
      <ymax>2052.0</ymax>
    </bndbox>
  </object>
  <object>
    <name>16_10</name>
    <difficult>0</difficult>
    <bndbox>
      <xmin>1064.0</xmin>
      <ymin>1957.0</ymin>
      <xmax>1099.0</xmax>
      <ymax>2053.0</ymax>
    </bndbox>
  </object>
  <object>
    <name>16_9</name>
    <difficult>0</difficult>
    <bndbox>
      <xmin>1145.0</xmin>
      <ymin>1964.0</ymin>
      <xmax>1169.0</xmax>
      <ymax>2053.0</ymax>
    </bndbox>
  </object>
  <object>
    <name>16_10</name>
    <difficult>0</difficult>
    <bndbox>
      <xmin>1215.0</xmin>
      <ymin>1957.0</ymin>
      <xmax>1242.0</xmax>
      <ymax>2053.0</ymax>
    </bndbox>
  </object>
  <object>
    <name>16_9</name>
    <difficult>0</difficult>
    <bndbox>
      <xmin>1287.0</xmin>
      <ymin>1964.0</ymin>
      <xmax>1311.0</xmax>
      <ymax>2053.0</ymax>
    </bndbox>
  </object>
  <object>
    <name>16_8</name>
    <difficult>0</difficult>
    <bndbox>
      <xmin>1348.0</xmin>
      <ymin>1972.0</ymin>
      <xmax>1382.0</xmax>
      <ymax>2052.0</ymax>
    </bndbox>
  </object>
  <object>
    <name>8_7</name>
    <difficult>0</difficult>
    <bndbox>
      <xmin>1462.0</xmin>
      <ymin>1981.0</ymin>
      <xmax>1487.0</xmax>
      <ymax>2051.0</ymax>
    </bndbox>
  </object>
  <object>
    <name>8_14</name>
    <difficult>0</difficult>
    <bndbox>
      <xmin>1611.0</xmin>
      <ymin>1924.0</ymin>
      <xmax>1647.0</xmax>
      <ymax>2053.0</ymax>
    </bndbox>
  </object>
  <object>
    <name>mf</name>
    <difficult>0</difficult>
    <bndbox>
      <xmin>1605.0</xmin>
      <ymin>2060.0</ymin>
      <xmax>1663.0</xmax>
      <ymax>2100.0</ymax>
    </bndbox>
  </object>
  <object>
    <name>Gclef</name>
    <difficult>0</difficult>
    <bndbox>
      <xmin>1702.0</xmin>
      <ymin>1967.0</ymin>
      <xmax>1737.0</xmax>
      <ymax>2070.0</ymax>
    </bndbox>
  </object>
  <object>
    <name>4_7</name>
    <difficult>0</difficult>
    <bndbox>
      <xmin>1778.0</xmin>
      <ymin>1980.0</ymin>
      <xmax>1804.0</xmax>
      <ymax>2051.0</ymax>
    </bndbox>
  </object>
  <object>
    <name>Rests8</name>
    <difficult>0</difficult>
    <bndbox>
      <xmin>2139.0</xmin>
      <ymin>1965.0</ymin>
      <xmax>2165.0</xmax>
      <ymax>1999.0</ymax>
    </bndbox>
  </object>
  <object>
    <name>8_6</name>
    <difficult>0</difficult>
    <bndbox>
      <xmin>2298.0</xmin>
      <ymin>1980.0</ymin>
      <xmax>2322.0</xmax>
      <ymax>2057.0</ymax>
    </bndbox>
  </object>
  <object>
    <name>4_8</name>
    <difficult>0</difficult>
    <bndbox>
      <xmin>2456.0</xmin>
      <ymin>1972.0</ymin>
      <xmax>2481.0</xmax>
      <ymax>2052.0</ymax>
    </bndbox>
  </object>
  <object>
    <name>4_-1_1</name>
    <difficult>0</difficult>
    <bndbox>
      <xmin>686.0</xmin>
      <ymin>955.0</ymin>
      <xmax>716.0</xmax>
      <ymax>1043.0</ymax>
    </bndbox>
  </object>
  <object>
    <name>4_-3_-1</name>
    <difficult>0</difficult>
    <bndbox>
      <xmin>1123.0</xmin>
      <ymin>956.0</ymin>
      <xmax>1154.0</xmax>
      <ymax>1059.0</ymax>
    </bndbox>
  </object>
  <object>
    <name>4_-1_1</name>
    <difficult>0</difficult>
    <bndbox>
      <xmin>2419.0</xmin>
      <ymin>952.0</ymin>
      <xmax>2448.0</xmax>
      <ymax>1043.0</ymax>
    </bndbox>
  </object>
</annotation>
